{
  "configVersion": 1,
  "timestamp": 1554248242336,
  "index": "/index.html",
  "assetGroups": [
    {
      "name": "app",
      "installMode": "prefetch",
      "updateMode": "prefetch",
      "urls": [
        "/es2015-polyfills.4a4cfea0ce682043f4e9.js",
        "/favicon.ico",
        "/index.html",
        "/main.63f6d69adf27282d5724.js",
        "/polyfills.407a467dedb63cfdd103.js",
        "/runtime.a5dd35324ddfd942bef1.js",
        "/scripts.968f55bfb751cd0febb2.js",
        "/styles.ef126f550e80449d719c.css"
      ],
      "patterns": []
    },
    {
      "name": "assets",
      "installMode": "lazy",
      "updateMode": "prefetch",
      "urls": [
        "/01.0a3750e6fdb29fcd632e.png",
        "/02.351bd6828f980ec53eb3.png",
        "/03.e438ea2aabdb1087dc4f.png",
        "/04.0284d042a6c29213aaa1.png",
        "/05.5014f9cce435c71ade63.png",
        "/06.21612b9d3e9d84e7e876.png",
        "/07.f8da0281186df8f17f73.png",
        "/08.975f7e0074400e7561ba.png",
        "/09.fd19309a1932b4751387.png",
        "/Roboto-Bold.39b2c3031be6b4ea96e2.woff2",
        "/Roboto-Bold.dc81817def276b4f2139.woff",
        "/Roboto-Bold.e31fcf1885e371e19f57.ttf",
        "/Roboto-Bold.ecdd509cadbf1ea78b8d.eot",
        "/Roboto-Light.3b813c2ae0d04909a33a.woff",
        "/Roboto-Light.46e48ce0628835f68a73.ttf",
        "/Roboto-Light.69f8a0617ac472f78e45.woff2",
        "/Roboto-Light.a990f611f2305dc12965.eot",
        "/Roboto-Medium.4d9f3f9e5195e7b074bb.eot",
        "/Roboto-Medium.574fd0b50367f886d359.woff2",
        "/Roboto-Medium.894a2ede85a483bf9bed.ttf",
        "/Roboto-Medium.fc78759e93a6cac50458.woff",
        "/Roboto-Regular.2751ee43015f9884c364.woff2",
        "/Roboto-Regular.30799efa5bf74129468a.eot",
        "/Roboto-Regular.ba3dcd8903e3d0af5de7.woff",
        "/Roboto-Regular.df7b648ce5356ea1ebce.ttf",
        "/Roboto-Thin.7500519de3d82e33d158.woff",
        "/Roboto-Thin.94998475f6aea65f5584.ttf",
        "/Roboto-Thin.954bbdeb86483e4ffea0.woff2",
        "/Roboto-Thin.dfe56a876d0282555d1e.eot",
        "/arrow_left.270f72df47e036d9cfa1.svg",
        "/arrow_right.d9ccc77c8240ad0dc272.svg",
        "/assets/icons/baseline-alarm-24px.svg",
        "/assets/icons/baseline-attach_file-24px.svg",
        "/assets/icons/baseline-attachment-24px.svg",
        "/assets/icons/baseline-audiotrack-24px.svg",
        "/assets/icons/baseline-clear-24px.svg",
        "/assets/icons/baseline-cloud_upload-24px.svg",
        "/assets/icons/baseline-done-24px.svg",
        "/assets/icons/baseline-how_to_reg-24px.svg",
        "/assets/icons/baseline-keyboard_backspace-24px.svg",
        "/assets/icons/baseline-location_on-24px.svg",
        "/assets/icons/baseline-mail_outline-24px.svg",
        "/assets/icons/baseline-navigate_before-24px.svg",
        "/assets/icons/baseline-navigate_next-24px.svg",
        "/assets/icons/baseline-notes-24px.svg",
        "/assets/icons/baseline-perm_contact_calendar-24px.svg",
        "/assets/icons/baseline-person-24px.svg",
        "/assets/icons/baseline-phone-24px.svg",
        "/assets/icons/baseline-photo-24px.svg",
        "/assets/icons/baseline-play_circle_outline-24px.svg",
        "/assets/icons/baseline-sentiment_very_dissatisfied-24px.svg",
        "/assets/icons/baseline-share-24px.svg",
        "/assets/icons/baseline-volume_mute-24px.svg",
        "/assets/icons/file_upload_48px.svg",
        "/assets/icons/file_upload_black_24x24.png",
        "/assets/icons/icon-128x128.png",
        "/assets/icons/icon-144x144.png",
        "/assets/icons/icon-152x152.png",
        "/assets/icons/icon-192x192.png",
        "/assets/icons/icon-384x384.png",
        "/assets/icons/icon-512x512.png",
        "/assets/icons/icon-72x72.png",
        "/assets/icons/icon-96x96.png",
        "/assets/logos/FacebookLogo.png",
        "/assets/logos/SpotifyLogo3.png",
        "/assets/logos/YoutubeLogo.png",
        "/assets/logos/logoHDM.png",
        "/fa-brands-400.4b115e1153a9ea339d6a.woff2",
        "/fa-brands-400.80533988ff5fecd5be26.svg",
        "/fa-brands-400.b90365bccdabd68c6c03.woff",
        "/fa-brands-400.c39278f7abfc798a2415.ttf",
        "/fa-brands-400.d9d17590c975aad1be0d.eot",
        "/fa-regular-400.414ff5daad323a1c47c5.eot",
        "/fa-regular-400.5dd3976cb5d61e2e561f.woff",
        "/fa-regular-400.65779ebcc35604a25c2b.woff2",
        "/fa-regular-400.e7e957c87c454bccaa3b.svg",
        "/fa-regular-400.f6c6f6c8cb7784254ad0.ttf",
        "/fa-solid-900.462806316fea535a6a57.woff2",
        "/fa-solid-900.61969d433bf265b9717a.woff",
        "/fa-solid-900.82905d8d1c06969df11c.svg",
        "/fa-solid-900.b5596f4d339f99e3d69b.eot",
        "/fa-solid-900.b70cea0339374107969e.ttf"
      ],
      "patterns": []
    }
  ],
  "dataGroups": [],
  "hashTable": {
    "/01.0a3750e6fdb29fcd632e.png": "7c046ea4b1669da4eb81acccd7fc58b00201543d",
    "/02.351bd6828f980ec53eb3.png": "9775bb2755b51c9eb03a3057eaf3914dc3149a6b",
    "/03.e438ea2aabdb1087dc4f.png": "c284f2c9ece402ccc1301b4301252476864235c0",
    "/04.0284d042a6c29213aaa1.png": "2816672fcbef8e08b431d600f26b119e2122eaa6",
    "/05.5014f9cce435c71ade63.png": "8d9fe47653c2615fd4a1e861e882e2efdb0f34a0",
    "/06.21612b9d3e9d84e7e876.png": "9d566536e859c18075d00e7f8cd6c490d310c089",
    "/07.f8da0281186df8f17f73.png": "078e49f4fa97e117da76cbef2b492e8cf92d0d45",
    "/08.975f7e0074400e7561ba.png": "b3916a95cb81602b7bd41eaefa92eb3a8fd39b70",
    "/09.fd19309a1932b4751387.png": "4d1c1ec2c710745ddcc43fdd0ae41d3095398a77",
    "/Roboto-Bold.39b2c3031be6b4ea96e2.woff2": "933b866d09c2b087707a98dab64b3888865eeb96",
    "/Roboto-Bold.dc81817def276b4f2139.woff": "ee99cd87a59a9a5d4092c83232bb3eec67547425",
    "/Roboto-Bold.e31fcf1885e371e19f57.ttf": "47327df0f35e7cd7c8645874897a7449697544ae",
    "/Roboto-Bold.ecdd509cadbf1ea78b8d.eot": "a76cd602f5188b9fbd4ba7443dcb9c064e3dbf10",
    "/Roboto-Light.3b813c2ae0d04909a33a.woff": "6300f659be9e834ab263efe2fb3c581d48b1e7b2",
    "/Roboto-Light.46e48ce0628835f68a73.ttf": "e321c183e2b75ee19813892b7bac8d7c411cb88a",
    "/Roboto-Light.69f8a0617ac472f78e45.woff2": "bbdc28b887400fcb340b504ec2904993af42a5d7",
    "/Roboto-Light.a990f611f2305dc12965.eot": "42fe156996197e5eb0c0264c5d1bb3b4681f4595",
    "/Roboto-Medium.4d9f3f9e5195e7b074bb.eot": "1517f4b6e1c5d0e5198f937557253aac8fab0416",
    "/Roboto-Medium.574fd0b50367f886d359.woff2": "6cc1b73571af9e827c4e7e91418f476703cd4c4b",
    "/Roboto-Medium.894a2ede85a483bf9bed.ttf": "6060ca726b9760b76f7c347dce9d2fa1fe42ec92",
    "/Roboto-Medium.fc78759e93a6cac50458.woff": "d45f84922131364989ad6578c7a06b6b4fc22c34",
    "/Roboto-Regular.2751ee43015f9884c364.woff2": "ed1558b0541f5e01ce48c7db1588371b990eec19",
    "/Roboto-Regular.30799efa5bf74129468a.eot": "77ae3e980ec03863ebe2587a8ef9ddfd06941db0",
    "/Roboto-Regular.ba3dcd8903e3d0af5de7.woff": "74734dde8d94e7268170f9b994dedfbdcb5b3a15",
    "/Roboto-Regular.df7b648ce5356ea1ebce.ttf": "824b5480c977a8166e177e5357d13164ccc45f47",
    "/Roboto-Thin.7500519de3d82e33d158.woff": "fbc3e71d456c96667d8082ab910e3946ef89240b",
    "/Roboto-Thin.94998475f6aea65f5584.ttf": "173ed64528b4d010a76d8d38deb1d7e7eed58eda",
    "/Roboto-Thin.954bbdeb86483e4ffea0.woff2": "2449e3dac5ddb7c3da8bb07450493b62d052758c",
    "/Roboto-Thin.dfe56a876d0282555d1e.eot": "0790a51a848dbe7292c98f9d0459218bf1a8ffdd",
    "/arrow_left.270f72df47e036d9cfa1.svg": "fb5b615955042a7c6aa16b1f0e8dcbdb279a8ac0",
    "/arrow_right.d9ccc77c8240ad0dc272.svg": "fac5123a15d035a642b74740b89636e2ace09810",
    "/assets/icons/baseline-alarm-24px.svg": "c756d56f8c6a48e0c6007527f9ff67555a931e76",
    "/assets/icons/baseline-attach_file-24px.svg": "60b63b7b7b44c14ba452164dc87b5001ca4bad84",
    "/assets/icons/baseline-attachment-24px.svg": "57f25c4fad55615b781be0cd978d7eaef1f04d76",
    "/assets/icons/baseline-audiotrack-24px.svg": "8d7f00b9284974e05b860bf2c440f2e391361cc5",
    "/assets/icons/baseline-clear-24px.svg": "1af37c1b27947b7d73e99de325566933d19a887c",
    "/assets/icons/baseline-cloud_upload-24px.svg": "4b438175000077e8ba21580324f467e4fde09657",
    "/assets/icons/baseline-done-24px.svg": "2d14843522ed5557f7ebf0509b437b1518b2f1fb",
    "/assets/icons/baseline-how_to_reg-24px.svg": "33387c5b79eb1e283f81dc7fd5514e6077a51f18",
    "/assets/icons/baseline-keyboard_backspace-24px.svg": "5af938f4333299d897bdfbd8ba2e5d6a5544b857",
    "/assets/icons/baseline-location_on-24px.svg": "cff8e274630ec95cad4913413aa3d3e17b917fca",
    "/assets/icons/baseline-mail_outline-24px.svg": "8aa1b09ee0d9ab229948e13278db42cbff777607",
    "/assets/icons/baseline-navigate_before-24px.svg": "84849e5d390da057a976cc26297030284d5f41a1",
    "/assets/icons/baseline-navigate_next-24px.svg": "defacacf10e081bfad75ff96cd9032c00efe4339",
    "/assets/icons/baseline-notes-24px.svg": "c98ec0f2ab92aa4bac2d8d3d28479ab57dc9635b",
    "/assets/icons/baseline-perm_contact_calendar-24px.svg": "004677a90c3206e7bd7995549d5253e3f9cc3060",
    "/assets/icons/baseline-person-24px.svg": "e00a7a03344ce21c927ec64404a03e7e7c678985",
    "/assets/icons/baseline-phone-24px.svg": "cde0d4617b84d627f29ff2fc186083c825e517b3",
    "/assets/icons/baseline-photo-24px.svg": "f349c5111676d5a8ac5b789670564bcaba2b8c41",
    "/assets/icons/baseline-play_circle_outline-24px.svg": "a9afc268951d47c710e3cc7d8dbbe5093178c3f3",
    "/assets/icons/baseline-sentiment_very_dissatisfied-24px.svg": "abf8001fa82a89e984e001fb5a7be48b7b05c790",
    "/assets/icons/baseline-share-24px.svg": "09451a2580ed1c993d8c955dc877481cc8203cf2",
    "/assets/icons/baseline-volume_mute-24px.svg": "9ae2f4dcfcfd2b5548a2ed3ccbea77a48880a6b3",
    "/assets/icons/file_upload_48px.svg": "03e0e9c5b19bdda53750510eb1561cc3801db788",
    "/assets/icons/file_upload_black_24x24.png": "bc01835c608084182ec627fca107ba8ee6266ea7",
    "/assets/icons/icon-128x128.png": "dae3b6ed49bdaf4327b92531d4b5b4a5d30c7532",
    "/assets/icons/icon-144x144.png": "b0bd89982e08f9bd2b642928f5391915b74799a7",
    "/assets/icons/icon-152x152.png": "7479a9477815dfd9668d60f8b3b2fba709b91310",
    "/assets/icons/icon-192x192.png": "1abd80d431a237a853ce38147d8c63752f10933b",
    "/assets/icons/icon-384x384.png": "329749cd6393768d3131ed6304c136b1ca05f2fd",
    "/assets/icons/icon-512x512.png": "559d9c4318b45a1f2b10596bbb4c960fe521dbcc",
    "/assets/icons/icon-72x72.png": "c457e56089a36952cd67156f9996bc4ce54a5ed9",
    "/assets/icons/icon-96x96.png": "3914125a4b445bf111c5627875fc190f560daa41",
    "/assets/logos/FacebookLogo.png": "73f011228da41a6d064450fd8ab99ad27e7dfa14",
    "/assets/logos/SpotifyLogo3.png": "1f5125f878c8ef7f26f2df4173667eb4e09db05e",
    "/assets/logos/YoutubeLogo.png": "7478cee1c4025550471874d66945ce3300795dc4",
    "/assets/logos/logoHDM.png": "69e949521f0c467ea4c6571b2513bfb7d8ff70f5",
    "/es2015-polyfills.4a4cfea0ce682043f4e9.js": "b7a81c61d32b0b12737f0c13f45973ba391cd7f9",
    "/fa-brands-400.4b115e1153a9ea339d6a.woff2": "f988b2efe9434b0af28943708d33dd3afad9a5ba",
    "/fa-brands-400.80533988ff5fecd5be26.svg": "94b435b77d62b21bbb378d9a4dbc18494225eb0a",
    "/fa-brands-400.b90365bccdabd68c6c03.woff": "ead05c8f530e600a8e27cab0ff7065d7a41b7b0f",
    "/fa-brands-400.c39278f7abfc798a2415.ttf": "69b73df3c8992a93859246065a267a05bfd8cf56",
    "/fa-brands-400.d9d17590c975aad1be0d.eot": "077fb9ea340316075962ba08e4fdc96eb2e4df07",
    "/fa-regular-400.414ff5daad323a1c47c5.eot": "43350c3fa2db974faa8c275c1a1d35e5973ddf98",
    "/fa-regular-400.5dd3976cb5d61e2e561f.woff": "52442e07d8cfc65daeefb08d3d7f64b8331b57e0",
    "/fa-regular-400.65779ebcc35604a25c2b.woff2": "fbb0d9d51850d824d7eba66e0e210c778d6d42f5",
    "/fa-regular-400.e7e957c87c454bccaa3b.svg": "67132d14a641ad8e59570cc37310c6fc777987a5",
    "/fa-regular-400.f6c6f6c8cb7784254ad0.ttf": "9706453c3ea9b73e7c08b3be1e7c716d655cf916",
    "/fa-solid-900.462806316fea535a6a57.woff2": "80644191098f863f25be27841c0d92c452cf2327",
    "/fa-solid-900.61969d433bf265b9717a.woff": "594f1d426bbb705028696be1686176508b04793c",
    "/fa-solid-900.82905d8d1c06969df11c.svg": "a24f75395c61216cb50d17e9c1d159984a464097",
    "/fa-solid-900.b5596f4d339f99e3d69b.eot": "6275300c533b525bd590a7e8190ee00c67928313",
    "/fa-solid-900.b70cea0339374107969e.ttf": "3f760416638f6459ade7251b80fd7bc27d6ad1c6",
    "/favicon.ico": "84161b857f5c547e3699ddfbffc6d8d737542e01",
    "/index.html": "3c01c00442dea57958e7057444c49afd3fafec48",
    "/main.63f6d69adf27282d5724.js": "40ba9141f5b88142aa71ee821babc0b32dd6be08",
    "/polyfills.407a467dedb63cfdd103.js": "ffa449995bf2eba2ccd0a002417214f7eb75e7b5",
    "/runtime.a5dd35324ddfd942bef1.js": "b62956c2192bfe5516d6374e753773901ed50ec5",
    "/scripts.968f55bfb751cd0febb2.js": "8cff919624f4590879d1564653ac7c73c135e960",
    "/styles.ef126f550e80449d719c.css": "b5027de91989b7c6380b9813f45997d7a4bbfdb3"
  },
  "navigationUrls": [
    {
      "positive": true,
      "regex": "^\\/.*$"
    },
    {
      "positive": false,
      "regex": "^\\/(?:.+\\/)?[^/]*\\.[^/]*$"
    },
    {
      "positive": false,
      "regex": "^\\/(?:.+\\/)?[^/]*__[^/]*$"
    },
    {
      "positive": false,
      "regex": "^\\/(?:.+\\/)?[^/]*__[^/]*\\/.*$"
    }
  ]
}